odoo/addons/analytic_product_category/README.rst
odoo/addons/analytic_product_category/__init__.py
odoo/addons/analytic_product_category/__manifest__.py
odoo/addons/analytic_product_category/init_hook.py
odoo/addons/analytic_product_category/i18n/analytic_product_category.pot
odoo/addons/analytic_product_category/i18n/ca.po
odoo/addons/analytic_product_category/i18n/es.po
odoo/addons/analytic_product_category/models/__init__.py
odoo/addons/analytic_product_category/models/analytic.py
odoo/addons/analytic_product_category/static/description/icon.png
odoo/addons/analytic_product_category/views/analytic.xml
odoo11_addon_analytic_product_category-11.0.1.0.0.99.dev6.dist-info/METADATA
odoo11_addon_analytic_product_category-11.0.1.0.0.99.dev6.dist-info/RECORD
odoo11_addon_analytic_product_category-11.0.1.0.0.99.dev6.dist-info/WHEEL
odoo11_addon_analytic_product_category-11.0.1.0.0.99.dev6.dist-info/top_level.txt
